odoo/addons/payroll_account/README.rst
odoo/addons/payroll_account/__init__.py
odoo/addons/payroll_account/__manifest__.py
odoo/addons/payroll_account/demo/hr_payroll_account_demo.xml
odoo/addons/payroll_account/i18n/af.po
odoo/addons/payroll_account/i18n/am.po
odoo/addons/payroll_account/i18n/ar.po
odoo/addons/payroll_account/i18n/az.po
odoo/addons/payroll_account/i18n/bg.po
odoo/addons/payroll_account/i18n/bn.po
odoo/addons/payroll_account/i18n/bs.po
odoo/addons/payroll_account/i18n/ca.po
odoo/addons/payroll_account/i18n/cs.po
odoo/addons/payroll_account/i18n/da.po
odoo/addons/payroll_account/i18n/de.po
odoo/addons/payroll_account/i18n/el.po
odoo/addons/payroll_account/i18n/en_GB.po
odoo/addons/payroll_account/i18n/es.po
odoo/addons/payroll_account/i18n/es_BO.po
odoo/addons/payroll_account/i18n/es_CL.po
odoo/addons/payroll_account/i18n/es_CO.po
odoo/addons/payroll_account/i18n/es_CR.po
odoo/addons/payroll_account/i18n/es_DO.po
odoo/addons/payroll_account/i18n/es_EC.po
odoo/addons/payroll_account/i18n/es_PE.po
odoo/addons/payroll_account/i18n/es_PY.po
odoo/addons/payroll_account/i18n/es_VE.po
odoo/addons/payroll_account/i18n/et.po
odoo/addons/payroll_account/i18n/eu.po
odoo/addons/payroll_account/i18n/fa.po
odoo/addons/payroll_account/i18n/fi.po
odoo/addons/payroll_account/i18n/fil.po
odoo/addons/payroll_account/i18n/fo.po
odoo/addons/payroll_account/i18n/fr.po
odoo/addons/payroll_account/i18n/fr_CA.po
odoo/addons/payroll_account/i18n/gl.po
odoo/addons/payroll_account/i18n/gu.po
odoo/addons/payroll_account/i18n/he.po
odoo/addons/payroll_account/i18n/hr.po
odoo/addons/payroll_account/i18n/hu.po
odoo/addons/payroll_account/i18n/id.po
odoo/addons/payroll_account/i18n/is.po
odoo/addons/payroll_account/i18n/it.po
odoo/addons/payroll_account/i18n/ja.po
odoo/addons/payroll_account/i18n/ka.po
odoo/addons/payroll_account/i18n/kab.po
odoo/addons/payroll_account/i18n/km.po
odoo/addons/payroll_account/i18n/ko.po
odoo/addons/payroll_account/i18n/lo.po
odoo13_addon_payroll_account-13.0.1.0.1.dev11.dist-info/METADATA
odoo13_addon_payroll_account-13.0.1.0.1.dev11.dist-info/WHEEL
odoo13_addon_payroll_account-13.0.1.0.1.dev11.dist-info/top_level.txt
odoo13_addon_payroll_account-13.0.1.0.1.dev11.dist-info/RECORD
